{"cameraMode":{"drawMode":0,"name":"Shaded","section":"Shading Mode"},"sceneLighting":true,"audioPlay":false,"sceneViewState":{"showFog":true,"showMaterialUpdate":false,"showSkybox":true,"showFlares":true,"showImageEffects":true,"showParticleSystems":true},"in2DMode":false,"pivot":{"x":25.265052795410158,"y":19.41661262512207,"z":-6.152012825012207},"rotation":{"x":-0.27758920192718508,"y":0.5115908980369568,"z":-0.17928233742713929,"w":-0.7934216856956482},"size":1.969454288482666,"orthographic":false}