{"cameraMode":{"drawMode":0,"name":"Shaded","section":"Shading Mode"},"sceneLighting":false,"audioPlay":false,"sceneViewState":{"showFog":true,"showMaterialUpdate":false,"showSkybox":false,"showFlares":true,"showImageEffects":true,"showParticleSystems":true},"in2DMode":false,"pivot":{"x":116.79347229003906,"y":4.530922889709473,"z":140.1621856689453},"rotation":{"x":0.12614618241786958,"y":0.6366738080978394,"z":-0.10491086542606354,"w":0.7538533210754395},"size":2.443777561187744,"orthographic":false}